equivalent_llm-0.4.0.dist-info/METADATA
equivalent_llm-0.4.0.dist-info/WHEEL
equivalent_llm-0.4.0.dist-info/licenses/LICENSE
equivalent_llm/__init__.py
equivalent_llm/engine/__init__.py
equivalent_llm/engine/openai.py
equivalent_llm/engine/pet.py
equivalent_llm/function/v1/__init__.py
equivalent_llm/function/v2/__init__.py
equivalent_llm/function_call/__init__.py
equivalent_llm/function_call/v1/__init__.py
equivalent_llm/function_call/v2/__init__.py
equivalent_llm/parse/__init__.py
equivalent_llm/reservation.py
equivalent_llm/testers/__init__.py
equivalent_llm/user.py
equivalent_llm-0.4.0.dist-info/RECORD
