Metadata-Version: 2.1
Name: equivalent_llm
Version: 0.4.0
Summary: Validation tool to compare a generated context by sLLM to reference context
Author-Email: Sung Gon Yi <skonmeme@sk.com>
License: BSD-3
Classifier: Programming Language :: Python :: 3
Classifier: License :: OSI Approved :: BSD License
Classifier: Operating System :: OS Independent
Project-URL: Homepage, https://github.com/sktaiflow/equivalent_llm
Project-URL: Issues, https://github.com/sktaiflow/equivalent_llm/issues
Requires-Python: >=3.10
Requires-Dist: langchain-core>=0.1.30
Requires-Dist: langchain>=0.1.11
Requires-Dist: langchain-community>=0.0.27
Requires-Dist: langchain-openai>=0.0.8
Requires-Dist: openai>=1.13.3
Requires-Dist: pydantic>=2.6.3
Requires-Dist: pytest>=8.1.1
Requires-Dist: pytest-mock>=3.12.0
Requires-Dist: ruff>=0.3.2
Requires-Dist: tqdm>=4.66.2
